lei_google_scholar/__init__.py
lei_google_scholar/core.py
lei_google_scholar/mcp_server.py
lei_google_scholar-0.1.0.dist-info/METADATA
lei_google_scholar-0.1.0.dist-info/WHEEL
lei_google_scholar-0.1.0.dist-info/entry_points.txt
lei_google_scholar-0.1.0.dist-info/top_level.txt
lei_google_scholar-0.1.0.dist-info/RECORD
