Metadata-Version: 2.4
Name: lei-google-scholar
Version: 0.1.0
Summary: A Python package for searching Google Scholar with MCP server support
License: MIT
Project-URL: Homepage, https://github.com/yourusername/lei-google-scholar
Project-URL: Repository, https://github.com/yourusername/lei-google-scholar
Project-URL: Issues, https://github.com/yourusername/lei-google-scholar/issues
Classifier: Development Status :: 3 - Alpha
Classifier: Intended Audience :: Developers
Classifier: License :: OSI Approved :: MIT License
Classifier: Operating System :: OS Independent
Classifier: Programming Language :: Python :: 3
Classifier: Programming Language :: Python :: 3.10
Classifier: Programming Language :: Python :: 3.11
Classifier: Programming Language :: Python :: 3.12
Classifier: Programming Language :: Python :: 3.13
Requires-Python: >=3.10
Requires-Dist: scholarly>=1.7.0
Requires-Dist: mcp>=1.0.0
Provides-Extra: dev
Requires-Dist: pytest>=7.0.0; extra == "dev"
Requires-Dist: black>=23.0.0; extra == "dev"
Requires-Dist: flake8>=6.0.0; extra == "dev"
